README.md
setup.py
hypergrowth/__init__.py
hypergrowth.egg-info/PKG-INFO
hypergrowth.egg-info/SOURCES.txt
hypergrowth.egg-info/dependency_links.txt
hypergrowth.egg-info/requires.txt
hypergrowth.egg-info/top_level.txt
hypergrowth/framework/__init__.py