Metadata-Version: 2.1
Name: hypergrowth
Version: 1.7.0
Summary: Hypergrowth framework to build upon
Home-page: https://github.com/alex4u2nv/hypergrowth
Author: Alexander Mahabir
Author-email: alex.mahabir@gmail.com
License: UNKNOWN
Project-URL: Bug Tracker, https://github.com/alex4u2nv/hypergrowth/issues
Platform: UNKNOWN
Classifier: Programming Language :: Python :: 3
Classifier: License :: OSI Approved :: MIT License
Classifier: Operating System :: OS Independent
Requires-Python: >=3.8
